freeplane.py
freeplane_io-0.10.1.dist-info/LICENSE.txt
freeplane_io-0.10.1.dist-info/METADATA
freeplane_io-0.10.1.dist-info/WHEEL
freeplane_io-0.10.1.dist-info/top_level.txt
freeplane_io-0.10.1.dist-info/RECORD
