Metadata-Version: 2.1
Name: freeplane-io
Version: 0.10.1
Summary: provide create, read, update and delete of freeplane nodes via file access
Home-page: https://github.com/nnako/freeplane-python-io
Author: nnako
Author-email: nnako@web.de
Classifier: Programming Language :: Python :: 3
Classifier: Programming Language :: Python :: 3.6
Classifier: Programming Language :: Python :: 3.7
Classifier: Programming Language :: Python :: 3.8
Classifier: Programming Language :: Python :: 3.9
Classifier: Programming Language :: Python :: 3.10
Classifier: Programming Language :: Python :: 3.11
Classifier: License :: OSI Approved :: GNU General Public License v2 or later (GPLv2+)
Classifier: Operating System :: OS Independent
License-File: LICENSE.txt
Requires-Dist: html2text (~=2020.1.16)
Requires-Dist: lxml
Provides-Extra: doc
Requires-Dist: sphinx (~=5.2.3) ; extra == 'doc'
